inpack/__init__.py
inpack/hstest.py
hstest-1.0.3.5.dist-info/METADATA
hstest-1.0.3.5.dist-info/WHEEL
hstest-1.0.3.5.dist-info/top_level.txt
hstest-1.0.3.5.dist-info/RECORD
